pn_sequence/__init__.py
pn_sequence-0.1.0.dist-info/LICENSE
pn_sequence-0.1.0.dist-info/METADATA
pn_sequence-0.1.0.dist-info/WHEEL
pn_sequence-0.1.0.dist-info/RECORD
